wire_exporter/__init__.py
wire_exporter/__main__.py
wire_exporter/capture.py
wire_exporter/cli.py
wire_exporter/filter.py
wire_exporter/prometheus.py
wire_exporter/filters/arp_reply.yaml
wire_exporter/filters/arp_request.yaml
wire_exporter/filters/broadcast.yaml
wire_exporter/filters/icmp6_cpam.yaml
wire_exporter/filters/icmp6_cpsm.yaml
wire_exporter/filters/icmp6_dst_unreach.yaml
wire_exporter/filters/icmp6_echo_reply.yaml
wire_exporter/filters/icmp6_echo_request.yaml
wire_exporter/filters/icmp6_emp.yaml
wire_exporter/filters/icmp6_haad_reply_message.yaml
wire_exporter/filters/icmp6_haad_request_message.yaml
wire_exporter/filters/icmp6_icmp_niq.yaml
wire_exporter/filters/icmp6_icmp_nir.yaml
wire_exporter/filters/icmp6_indam.yaml
wire_exporter/filters/icmp6_indsm.yaml
wire_exporter/filters/icmp6_mld.yaml
wire_exporter/filters/icmp6_mlq.yaml
wire_exporter/filters/icmp6_mlr_v1.yaml
wire_exporter/filters/icmp6_mlr_v2.yaml
wire_exporter/filters/icmp6_mpa.yaml
wire_exporter/filters/icmp6_mps.yaml
wire_exporter/filters/icmp6_mra.yaml
wire_exporter/filters/icmp6_mrs.yaml
wire_exporter/filters/icmp6_mrt.yaml
wire_exporter/filters/icmp6_na.yaml
wire_exporter/filters/icmp6_ns.yaml
wire_exporter/filters/icmp6_parameter_problem.yaml
wire_exporter/filters/icmp6_pckt_too_big.yaml
wire_exporter/filters/icmp6_ra.yaml
wire_exporter/filters/icmp6_redirect.yaml
wire_exporter/filters/icmp6_rpl.yaml
wire_exporter/filters/icmp6_rr.yaml
wire_exporter/filters/icmp6_rs.yaml
wire_exporter/filters/icmp6_time_exceeded.yaml
wire_exporter-0.1.7.dist-info/DESCRIPTION.rst
wire_exporter-0.1.7.dist-info/METADATA
wire_exporter-0.1.7.dist-info/RECORD
wire_exporter-0.1.7.dist-info/WHEEL
wire_exporter-0.1.7.dist-info/entry_points.txt
wire_exporter-0.1.7.dist-info/metadata.json
wire_exporter-0.1.7.dist-info/top_level.txt
